{
  "HITEEN카드": {
    "category": "카드",
    "pd_info": "\n* 발급대상\nHi teen을 보유한 본인 회원\n\n- 서비스한도\nHi teen 카드 이용한도 : 일 50만원, 월 200만원\n※ Hi teen 카드 이용한도와 Hi teen 이용한도는 각각 관리됩니다.\n※ Hi teen 카드 이용한도에 포함되는 금액은 Hi teen 카드를 통한 결제금액입니다.\n\n-  발급수수료\n3,000원 (최초 발급은 무료)\n\n- Hi teen 상품혜택\n편의점업종에서 결제금액 상관없이 이용할 때마다 100원씩 최대 10회 캐시백 (동일 브랜드별 1일 1회)\n캐시백 대상 편의점 브랜드 : GS25, CU, 세븐일레븐, 이마트24, 미니스탑\n온라인 업종에서 결제금액 상관없이 이용할 때마다 100원씩 최대 5회 캐시백 (1일 횟수 제한 없음)\n* 전월실적 상관없이 혜택 제공\n"
  },
  "KT멤버십더블혜택체크카드": {
    "category": "카드",
    "pd_info": "\n* KT멤버십 할인 받고, 차감된 멤버십 포인트 만큼 한번 더 캐시백\n| 전월 이용금액  | 영화/외식 | 편의점/쇼핑 | 통신요금 캐시백률 | 통신요금 캐시백 한도 | 총 캐시백 한도 |\n|----------|-------|--------|-----------|-------------|----------|\n| 20만원 이상  | 5천원   | 5천원    | 5%        | 5천원         | 1만 5천원   |\n| 50만원 이상  | 1만원   | 1만원    | 10%       | 1만원         | 3만원      |\n| 100만원 이상 | 2만원   | 2만원    | 20%       | 2만원         | 6만원      |\n\n* KT유∙무선 통신요금 5~20% 캐시백\n캐시백 대상 : 이동통신, 인터넷, IPTV, 집전화, 인터넷전화, 유무선 결합 상품, 와이브로\n| 전월 이용금액  | 캐시백률 | 캐시백 한도 |\n|----------|------|--------|\n| 20만원 이상  | 5%   | 5천원    |\n| 50만원 이상  | 10%  | 1만원    |\n| 100만원 이상 | 20%  | 2만원    |\n\n* 해외 결제 및 ATM 인출수수료 무료\n| 구분         | 해외서비스 수수료 |\n|------------|-----------|\n| 해외가맹점 결제 시 | 무료        |\n| 해외ATM 인출 시 | 무료        |\n\n* KT멤버십 제휴가맹점 할인\n\n* POP CARD 할인 및 GS&POINT 적립\nGS25편의점, GS수퍼마켓, GS fresh 등 POP CARD 제휴처에서 행사상품 할인 혜택이 제공됩니다.\nGS칼텍스, GS리테일, GS SHOP 등 GS&POINT 제휴처에서 통합 포인트 적립 혜택이 제공됩니다.\n"
  },
  "MY체크카드": {
    "category": "카드",
    "pd_info": "\n* 혜택안내\n매일매일 최대 5천원, 매월 최대 15만원까지 10가지 혜택 영역에서 결제 할 때마다 최대 500원 캐시백\n캐시백 대상 가맹점에서 최소 5천원 이상 결제 시, 최대 500원 캐시백이 지급됩니다.\n- 전월 실적 조건없이 300원\n- 전월 실적 30만원 이상 시 500원\n- 캐시백은 각 영역별 1일 1회 기준으로 제공됩니다.\n\n* 캐시백 영역 및 대상 가맹점\n\n| 편의 ∙ 생활    | GS25, CU, 세븐일레븐, 이마트24, 미니스톱, 올리브영, 다이소, 노브랜드 |\n|------------|-----------------------------------------------|\n| 커피 ∙ 음료    | 스타벅스, 투썸플레이스, 메가커피, 이디야, 빽다방, 공차, 메머드커피       |\n| 패스트푸드      | 맥도날드, 롯데리아, 버거킹, 서브웨이, KFC, 맘스터치, 쉐이크쉑        |\n| 베이커리 ∙ 디저트 | 파리바게뜨, 던킨도너츠, 뚜레쥬르, 이삭토스트, 베스킨라빈스, 설빙         |\n| 패션         | 지그재그, 무신사, 에이블리, 브랜디, SSF, W컨셉, ZARA          |\n| 영화         | CGV, 롯데시네마, 메가박스                              |\n| 도서         | 교보문고, 영풍문고, 알라딘, Yes24                        |\n| 택시         | 카카오택시, 타다                                     |\n| OTT        | 넷플릭스, 유튜브 프리미엄                                |\n| 어학         | YBM (TOEIC 등 어학시험)                            |\n"
  },
  "NH투자증권": {
    "category": "제휴",
    "pd_info": "\n* 이벤트 기간 : 2024년 1월 1일 ~ 1월 31일\n* 대상 : 이벤트 기간 내 케이뱅크에서 NH투자증권 나무(NAMUH) 증권계좌를 최초 개설한 고객 (주민등록번호 기준 NH투자증권 최초 신규)\n\n* 혜택\n1) 투자지원금 30달러\n신규 계좌개설 혜택인 투자지원금 $30은 케이뱅크 앱에서 증권계좌 개설 시 [혜택제공을 위한 선택동의] 개인(신용)정보 수집 및 이용 동의서에 동의하고 개설하신 후 NH투자증권 나무증권 앱에서 이벤트 신청 시 제공되며 국내주식 매매수수료, 해외주식 매매수수료 및 환전 우대 혜택은 자동 적용됩니다.\n국내 또는 해외주식 1회 이상 거래 시 이벤트 신청가능\n\n2) 국내주식 매매수수료 우대\n우대기간 : 개설일로부터 12개월\n최초 12개월 우대수수료율(2024년 1월 1일 기준)\n- 국내주식(코스피,코스닥,코넥스) : 0.0043319%\n- ETF/ETN/ELW : 0.0049010%\n\n3) 해외주식 매매수수료 0.09% + 환전우대 최대 우대율 적용 시 $1당 최대 0.5원\n우대기간 : 개설일로부터 12개월\n해외주식 우대수수료 대상국가 : 미국 (USD), 중국 (CNY), 홍콩 (HKD),일본(JPY), 영국(GBP),독일(EUR),호주(AUD) , 베트남(VND), 인도네시아(IDR) (9개국)\n환전우대 대상국가 : 미국(USD), 중국(CNY), 홍콩(HKD), 일본(JPY)\n환전우대는 자동환전과 수동환전 별로 다른 우대율이 적용됩니다.\n자동환전($1당 최대 0.5원): 원화 주문, 소수점 주문, 통합증거금 계좌 사용 시 적용\n"
  },
  "국민카드": {
    "category": "제휴",
    "pd_info": "\n* 상품안내\n-# 스타벅스 50% 청구할인\n스타벅스(사이렌오더 포함)\n\n※ 월 할인한도 1만원\n※ 상품권(선물하기 등) 및 선불카드(선불전자지급수단 포함) 충전 제외\n\n-#  구독 20% 청구할인\nYouTube Premium, 넷플릭스, 웨이브, 티빙\n\n※ 월 할인한도 3천원\n※ 공식 홈페이지 및 모바일(앱)을 통한 정기결제 시 제공 (간편결제 건 또는 앱스토어를 통한 인앱 결제 건 등은 제외)\n\n-# 배달 5% 청구할인\n배달의민족, 요기요\n\n※ 월 할인한도 5천원\n\n-#  온라인 간편결제 10% 청구할인\nKB Pay, 삼성페이, LG 페이, 카카오페이, 네이버페이, PAYCO, 쿠페이, 스마일페이, SSGPAY, L.pay\n\n※ 월 할인한도 3천원\n※ 국내 온라인 가맹점 결제 건에 한하며, 오프라인 매장 결제 건(QR/바코드 결제, 스마트폰 NFC, 카카오T, 택시 등)은 제외\n※ 스타벅스, 배달 청구할인 서비스와 중복 적용 가능하며 할인한도는 각각 차감\n\n-# 대중교통 5% 청구할인\n버스, 지하철\n※ 월 할인한도 3천원\n※ 시외버스, 고속버스, 공항버스 제외\n※ 이용대금명세서상 기재된 이용일 기준 서비스 적용\n"
  },
  "기분통장": {
    "category": "예금 · 적금",
    "pd_info": "\n* 상품요약\n가입대상: 당행 입출금통장을 보유한 실명의 개인 및 개인사업자(1인 최대 10계좌)\n예금종류: 입출금이 자유로운 예금\n가입금액: 보유한 플러스박스 계좌 잔액을 모두 합산하여 최대 10억원까지 입금 가능\n가입기간: 제한없음\n\n* 적용금리\n(조회기준일: 2024.02.02, 현재, 세전, 연%)\n적용금리 : 연 2.30%\n이자계산방법 : 일자별 최종 잔액에 대하여 약정된 금리를 적용한 일별이자를 합산\n이자결산지급일 : 매월 넷째주 토요일\n「바로 이자받기」 : 이자지급일이 도래하기 전이라도 최초 예금일(또는 지난 이자지급일)부터 「바로 이자받기」 신청 전일까지의 이자를 바로 받을 수 있습니다.\n이 예금으로 이자가 입금되며, 이자 입금 후 예금의 잔액이 가입금액 한도를 초과하는 경우 초과금액은 연결계좌로 자동 입금 됩니다.\n"
  },
  "롯데카드": {
    "category": "제휴",
    "pd_info": "\n* 상품안내\n\n| 구분    | 라이프 가맹점명                     | 캐시백률 |\n|-------|------------------------------|------|\n| 페이    | 네이버페이, 삼성페이                  | 5%   |\n| 배달·마켓 | 쿠팡이츠, 요기요, 배달의민족, 마켓컬리, 오아시스 | 10%  |\n| 멤버십   | 스마일클럽, 쿠팡 로켓와우클럽, 네이버플러스     | 10%  |\n| 스트리밍  | 넷플릭스, 디즈니플러스, 왓차, 웨이브, FLO   | 10%  |\n| 커피    | 스타벅스 사이렌오더                   | 50%  |\n| 대중교통  | 버스, 지하철                      | 50%  |\n\n- 전월 40만원 이상 사용 고객 대상 최대 한도 1만원\n"
  },
  "마이너스통장": {
    "category": "대출",
    "pd_info": "\n* 상품요약\n상품종류: 가계신용대출\n\n* 대출대상\n재직기간 6개월 이상, 연 환산소득 2,000만원 이상인 국민건강보험 가입 근로소득자\n(단, 일부 고객에 한해 재직기간 6개월 미만인 경우에도 대출 가능)\n케이뱅크 심사기준을 충족하는 고객\n\n* 대출한도\n최대 2억원\n\n* 상환방식 및 대출기간\n한도대출(마이너스통장): 1년(1년 단위로 10년까지 연장 가능)\n\n* 적용금리\n(조회기준일: 2024.02.02, 현재, 세전, 연%)\n| 대출금리            | 기준금리                       | 가산금리            |\n|-----------------|----------------------------|-----------------|\n| 연 5.36% ~ 12.72%  | KORIBOR(직전3영업일평균), 연 3.66% | 연 1.70% ~ 9.06% |\n"
  },
  "미래에셋증권": {
    "category": "제휴",
    "pd_info": "\n* 이벤트 기간 : 2024년 1월 1일 ~ 6월 30일\n\n* 혜택1. 개설축하금 1만원\n대상 : 이벤트 기간 내 케이뱅크에서 최초 신규로 미래에셋증권 주식계좌 개설한 고객\n*최초신규 : 주민등록번호 기준 미래에셋증권에 계좌를 개설한 적이 없는 고객\n\n* 혜택2-1. 투자지원금 2만원\n대상 : 이벤트 기간 내 케이뱅크에서 최초 신규로 미래에셋증권 주식계좌 개설한 고객 중 WELCOME 이벤트 신청자 (개설 이후 15일 이내 신청 필수)\n투자지원금 2만원을 이벤트 신청일로부터 16일 이내에 주식 매수에 사용하지 않을 시 다음 영업일에 전액 회수(출금)\n\n* 혜택2-2. 거래축하금 최대 18만원\n대상 : 이벤트 기간 내 케이뱅크에서 최초 신규로 미래에셋증권 주식계좌 개설 및 WELCOME 이벤트 신청자 중 해외주식 100만원 이상 매수한 고객\n거래 집계 기간동안 매수한 해외주식 금액에 해당되는 거래 축하금은 익월 20영업일 내 이벤트를 신청한 계좌로 지급(거래구간별 혜택금 중복지급 없음)\n- 해외주식 100만원 이상 ~ 1,000만원 미만 : 2만원\n- 해외주식 1,000만원 이상 ~ 1억원 미만 : 3만원\n- 해외주식 1억원 이상 ~ 3억원 미만 : 8만원\n- 해외주식 3억원 이상 ~ : 18만원\n\n* 혜택3. 수수료 혜택\n대상 : 미래에셋증권 최초신규 및 주식 휴면 고객 중 수수료 우대 혜택 이벤트 신청자\n(개설 이후 90일 이내 신청 필수)\n\n* 대상 : 최초신규 고객,  주민등록번호 기준 미래에셋증권에 계좌를 개설한 적이 없는 고객(구 미래에셋대우 / 대우증권 포함)\n"
  },
  "부동산자산관리서비스": {
    "category": "서비스",
    "pd_info": "\n\n부동산자산관리서비스는 아래 2가지 기능을 제공합니다.\n\n1. 우리집 변동알림\n고객이 전세로 등록한 아파트의 등기정보가 변경될 경우, 이를 탐지하고 안내하는 서비스로 전세사기 등 피해 우려가 있는 등기 변동이 발생하면 케이뱅크가 앱 푸시(Push)로 알림이 오는 서비스입니다. \n아파트만 가능하며 오피스텔이나 빌라 등 기타 부동산은 아직 서비스가 제공되지 않습니다.\n\n2. 우리동네 리포트\n설정해둔 아파트 단지 인근의 매매 및 전세가격 현황도 확인할 수 있습니다. 이를 통해 관심 지역의 아파트 매수·매도 타이밍도 잡아볼 수 있습니다."
  },
  "비상금대출": {
    "category": "대출",
    "pd_info": "\n* 상품요약\n상품종류: 가계신용대출\n\n* 대출대상\n재직기간 6개월 이상, 연 환산소득 2,000만원 이상인 국민건강보험 가입 근로소득자\n(단, 일부 고객에 한해 재직기간 6개월 미만인 경우에도 대출 가능)\n케이뱅크 심사기준을 충족하는 고신용자* 고객\n\n* 대출한도\n최대 3억원\n\n* 상환방식 및 대출기간\n원리금균등분할상환: 최장 10년(1,2,3,4,5,10년)\n만기일시상환: 1년(1년 단위로 10년까지 연장 가능)\n\n* 적용금리\n(조회기준일: 2024.02.02, 현재, 세전, 연%)\n| 대출금리            | 기준금리                       | 가산금리            |\n|-----------------|----------------------------|-----------------|\n| 연 4.87% ~ 6.46% | KORIBOR(직전3영업일평균), 연 3.66% | 연 1.21% ~ 2.80% |\n"
  },
  "사잇돌대출": {
    "category": "대출",
    "pd_info": "\n* 상품요약\n상품특징: 서울보증보험과의 협약대출로 서울보증보험이 발급하는 보험증권을 담보로 실행되는 대출\n\n* 대출대상\n만 19세 이상의 직장인 및 개인사업자\n직장인: 3개월 이상 재직하고 연소득이 1500만원 이상인 고객\n개인사업자: 단독명의 개인사업자로 휴∙폐업 없이 현재 6개월 이상 정상적으로 사업을 영위중에 있고, 홈택스 기준 직전년도 신고소득이 1,000만원 이상인 고객\n※ 단, 7월1일 이전 신청건은 전전년도 사업소득이 1,000만원 이상 신고되어 있어야 합니다.\n케이뱅크 내부 심사기준을 충족하는 고객\n서울보증보험 보험증권 발급이 가능한 고객\n\n* 대출한도\n최대 2,000만원\n\n* 상환방식 및 대출기간\n원리금균등상환: 원금과 이자를 합친 원리금을 매월 동일한 금액으로 상환하는 방식\n최대 5년\n\n* 적용금리\n(조회기준일: 2024.02.02, 현재, 세전, 연%)\n연 7.59% ~ 15.00%\n| 구분   | 적용금리                             |\n|------|----------------------------------|\n| 기준금리 | 금융채 연동금리 (6개월 3.65%, 12개월 3.62%) |\n| 가산금리 | 연 3.94%~11.38%                   |\n"
  },
  "사장님보증서대출": {
    "category": "SME",
    "pd_info": "\n* 상품요약\n상품종류: 개인사업자 운전자금대출\n대출대상: 사업기간이 1년 이상인 개인사업자\n대출한도: 최대 3천만원\n\n* 대출대상\n사업기간이 1년 이상인 개인사업자: 단독명의 개인사업자로 휴∙폐업 없이 현재 3개월 이상 연속된 매출이 있고, 신청일 기준 1주일 이내 매출이 있는 고객\n대표자 개인신용평점 745점 이상(신용보증신청 접수일 현재, NICE평가정보(주)기준)인 고객\n케이뱅크 내부 심사기준을 충족하는 고객\n신용보증재단 보증서 발급이 가능한 고객\n연체, 부도 등 신용도판단정보가 등록되지 않은 고객\n회생, 파산, 면책 등을 신청하거나 확정된 사실이 없는 고객\n케이뱅크에 손실을 끼친 이력 및 금융 사기와 사고 이력이 없는 고객\n사업장이 현재 운영 중이며, 보증 제한 업종(도박,유흥,오락,점술 등)에 해당되지 않는 고객\n별도의 법인을 운영하거나 공동대표로 등재되지 않은 개인사업자\n\n* 대출한도\n최대 3천만원 (최소 대출신청 가능금액 5백만원)\n\n* 상환방식 및 대출기간\n5년 (1년 거치, 4년 원금균등분할상환)\n\n* 적용금리\n(조회기준일: 2024.02.02, 현재, 세전, 연%)\n연 5.38%\n| 구분   | 적용금리                           |\n|------|--------------------------------|\n| 기준금리 | CD연동대출금리(3개월)(3.68%) 3개월 마다 변동 |\n| 가산금리 | 단일금리 1.70%           |\n"
  },
  "사장님신용대출": {
    "category": "SME",
    "pd_info": "\n* 상품요약\n상품종류: 개인사업자 운전자금대출\n대출대상: 사업기간이 1년 이상인 개인사업자\n대출한도: 최대 1억원\n\n* 대출대상\n사업기간이 1년 이상인 개인사업자: 단독명의 개인사업자로 휴∙폐업 없이 현재 3개월 이상 연속된 매출이 있고, 연소득 1천만원 이상인 개인사업자\n케이뱅크 내부 심사기준을 충족하는 고객\n연체, 부도 등 신용도판단정보가 등록되지 않은 고객\n회생, 파산, 면책 등을 신청하거나 확정된 사실이 없는 고객\n케이뱅크에 손실을 끼친 이력 및 금융 사기와 사고 이력이 없는 고객\n사업장이 현재 운영 중이며, 취급 불가 업종(도박,유흥,오락,점술 등)에 해당되지 않는 고객\n사업장에 법인 또는 공동대표가 등재되지 않는 개인 기업 고객\n\n* 대출한도\n최대 1억원(최소 대출신청 가능금액 1백만원)\n※ 월별 한도 소진 시 판매 조기 종료(익월 판매 재개)\n※ 대출한도의 경우 개인의 신용상태에 따라 차등 적용되며, 보유 중인 케이뱅크 대출 또는 타 금융기관 대출 (단기, 장기 카드대출 등 포함)에 따라 한도 차등 부여\n\n* 상환방식 및 대출기간\n만기일시상환: 1년(1년 단위로 10년까지 연장 가능)\n원리금균등분할상환: 최장 3년(1, 2, 3년)\n\n* 적용금리\n(조회기준일: 2024.02.02, 현재, 세전, 연%)\n연 5.31% ~ 7.39%\n| 구분   | 적용금리                           |\n|------|--------------------------------|\n| 기준금리 | CD연동대출금리(3개월)(3.68%) 3개월 마다 변동 |\n| 가산금리 | 최저 1.63% ~ 최고 3.71%            |\n"
  },
  "삼성카드": {
    "category": "제휴",
    "pd_info": "\n* 상품안내\n* 스트리밍·웹툰 50% 결제일 할인\n| 구분   | 할인 대상                                            |\n|------|--------------------------------------------------|\n| 스트리밍 | 넷플릭스, 유튜브 프리미엄, 디즈니+, 웨이브, 티빙, 왓챠, 멜론, FLO 정기결제건 |\n| 웹툰   | 카카오웹툰                                            |\n\n- 전월 이용금액대별 통합 월 할인한도\n| 40만원 이상 | 70만원 이상 | 100만원 이상 |\n|---------|---------|----------|\n| 5,000원  | 10,000원 | 15,000원  |\n\n* 교통·이동통신 10% 할인\n| 구분   | 할인 대상                                                                      |\n|------|----------------------------------------------------------------------------|\n| 교통   | 대중교통(버스, 지하철), 택시                                                          |\n| 이동통신 | SKT, KT, LG U+, 알뜰폰(SK텔링크, KT스카이 라이프, KT M모바일, 헬로모바일, 미디어로그) 이동통신요금 정기결제 건 |\n\n통합 월 할인한도: 5,000원\n전월 이용금액 40만원 이상 시 제공\n\n* 배달앱·커피전문점 10% 할인\n| 업종    | 할인 대상                   |\n|-------|-------------------------|\n| 배달앱   | 배달의민족, 요기요, 쿠팡이츠        |\n| 커피전문점 | 스타벅스, 투썸플레이스, 커피빈, 블루보틀 |\n통합 월 할인한도: 5,000원\n전월 이용금액 40만원 이상 시 제공\n\n* 여행플랫폼 10% 할인\n| 구분    | 할인 대상            |\n|-------|------------------|\n| 여행플랫폼 | 야놀자, 여기어때, 데일리호텔 |\n\n- 전월 이용금액대별 통합 월 할인한도\n| 40만원 이상 | 70만원 이상 | 100만원 이상 |\n|---------|---------|----------|\n| 5,000원  | 10,000원 | 15,000원  |\n\n* 트렌디 쇼핑 5% 할인\n| 구분       | 할인 대상                                     |\n|----------|-------------------------------------------|\n| 온라인 쇼핑몰  | 쿠팡, 티몬, 위메프, G마켓, 옥션, 11번가, 인터파크, 삼성카드 쇼핑 |\n| 온라인 패션몰  | 무신사, W컨셉, KREAM, 나이키닷컴                    |\n| 백화점      | 신세계백화점, 롯데백화점, 현대백화점                      |\n| 프리미엄 아울렛 | 신세계사이먼 프리미엄 아울렛, 롯데 프리미엄 아울렛, 현대 프리미엄 아울렛 |\n\n- 전월 이용금액대별 통합 월 할인한도\n| 40만원 이상 | 70만원 이상 | 100만원 이상 |\n|---------|---------|----------|\n| 5,000원  | 10,000원 | 15,000원  |\n"
  },
  "세금환급": {
    "category": "SME",
    "pd_info": "\n* 상품요약\n(개인/법인) 사업자를 위한 세금 환급 서비스\n\n- 상품상세\n사업자가 과거 사업소득에 대한 세금 신고하면서 놓쳤던 '세액공제'나 '세액감면' 항목들을 고도화된 AI기술을 활용해 찾아내고, \n비즈넵과 제휴한 세무전문가가 탐색 결과 값을 더블 체크해 누수 없는 환급을 도와 드립니다.\n개인 또는 법인 사업체를 운영하는 사장님이라면 '비즈넵 환급' 으로 숨은 환급금을 무료 조회할 수 있습니다.\n"
  },
  "신용대출": {
    "category": "대출",
    "pd_info": "\n* 상품요약\n상품종류: 가계신용대출\n\n* 대출대상\n재직기간 6개월 이상, 연 환산소득 2,000만원 이상인 국민건강보험 가입 근로소득자\n(단, 일부 고객에 한해 재직기간 6개월 미만인 경우에도 대출 가능)\n케이뱅크 심사기준을 충족하는 고신용자* 고객\n\n* 대출한도\n최대 3억원\n\n* 상환방식 및 대출기간\n원리금균등분할상환: 최장 10년(1,2,3,4,5,10년)\n만기일시상환: 1년(1년 단위로 10년까지 연장 가능)\n\n* 적용금리\n(조회기준일: 2024.02.02, 현재, 세전, 연%)\n| 대출금리            | 기준금리                       | 가산금리            |\n|-----------------|----------------------------|-----------------|\n| 연 4.87% ~ 6.46% | KORIBOR(직전3영업일평균), 연 3.66% | 연 1.21% ~ 2.80% |\n"
  },
  "심플카드": {
    "category": "제휴",
    "pd_info": "\n* 상품안내\n-# 기본 : 국내외 가맹점 0.8% 청구 할인\n전월실적 조건 및 할인한도 없음\n할인 제외 대상: 서비스 제공조건 참고\n기본 할인과 플러스 할인은 중복 적용 불가\n\n-# 플러스 : 생활 밀착 영역 1.5% 청구 할인\n| 생활 밀착 영역 | 적용 가맹점                                                       |\n|----------|--------------------------------------------------------------|\n| 온라인 간편결제 | 삼성페이, 네이버페이, 카카오페이, 스마일페이, 쿠페이, SSGPAY, SK Pay, L.pay, PAYCO |\n| 편의점      | GS25, CU, 세븐일레븐, 이마트24                                       |\n| 커피전문점    | 스타벅스, 커피빈, 투썸플레이스, 이디야, 폴바셋                                  |\n| 교통       | 후불교통요금(시내버스, 지하철), 택시                                        |\n| 이동통신요금   | KT, SKT, LGU+(자동이체)                                          |\n| 디지털      | 넷플릭스, 유투브 프리미엄, 웨이브, 티빙, 왓챠      \n\n전월실적 조건 및 할인한도 없음\n기본 할인과 플러스 할인은 중복 적용 불가\n"
  },
  "아파트담보대출": {
    "category": "대출",
    "pd_info": "\n* 상품요약\n상품종류: 가계담보대출\n신청제한: 안정적 판매를 위해 일별 신청건수 제한 있음\n\n* 대출대상\n본인 단독 또는 배우자 공동명의 아파트 소유 고객이거나 아파트를 구입하려는 고객\n근로소득자, 사업소득자, 연금소득자, 프리랜서 등 소득 확인이 가능한 고객\n당행 내부 심사기준을 충족하는 고객\n\n* 대출한도\nLTV/DTI/DSR 등 규제범위 내에서 아파트 소재지, 아파트 시세, 개인 소득 및 부채현황 등에 따라 차등 적용됩니다.\n구입자금 대출: 최대 10억원\n대출 갈아타기: 최대 10억원(보유한 주택담보대출의 대출금액 이내이며, 기존 대출 전액을 갈아타는 조건)\n생활안정자금 대출: 최대 10억원\n반환자금 대출 : 최대 10억원\n\n* 적용금리\n(조회기준일: 2024.02.02, 현재, 세전, 연%)\n| 기준금리                      | 가산금리         | 최저금리  | 최고금리  |\n|---------------------------|--------------|-------|-------|\n| 신규취급액기준 COFIX(6개월): 3.84% | 0.22% ~1.83% | 4.06% | 5.67% |\n| 신잔액기준 COFIX(3개월): 3.29%   | 0.15% ~1.77% | 3.44% | 5.06% |\n| 고정혼합금리: 3.81%             | 0.32% ~1.34% | 4.13% | 5.15% |\n"
  },
  "예금적금담보대출": {
    "category": "대출",
    "pd_info": "\n* 대출대상\n내국인 거주자로서, 당행에 본인명의 예금 · 적금 계좌를 보유한 개인 및 개인사업자\n\n* 대출한도\n가입한 예금 · 적금 계좌 잔액의 95% 범위 내에서 10만원 단위로 가능\n최소 대출신청 가능금액 10만원, 최대 5000만원 한도(1인당 최고 5000만원)\n\n- 상환방식\n만기일시상환\n한도대출(마이너스통장)\n\n* 적용금리\n(조회기준일: 2024.02.02, 현재, 세전, 연%)\n\n* 담보로 제공되는 예금 · 적금 상품금리 + 가산금리\n| 구분   | 적용금리                 |\n|------|----------------------|\n| 기준금리 | 예금 · 적금 상품금리         |\n| 가산금리 | 1.00% (한도대출 : 1.50%) |\n"
  },
  "전세대출": {
    "category": "대출",
    "pd_info": "\n- 상품 종류\n가계전세자금대출\n\n* 대출대상\n신청 상품별 가입조건과 공통조건을 충족한 고객\n\n[상품별 가입조건]\n-# 고정금리 전세대출\n1. 만 19세 이상 내국인\n2. 근로소득자(현 직장 6개월 이상 재직) 또는 소득금액증명원 발급이 가능한 사업소득자\n3. 부부합산 무주택인 고객\n\n-# 전세대출\n1. 만 19세 이상 내국인\n2. 근로소득자(현 직장 1년 이상 재직) 또는 소득금액증명원 발급이 가능한 사업소득자\n3. 부부합산 무주택 또는 1주택인 고객\n※ 2020.07.10 이후 투기지역 및 투기과열지구 내 시세 3억원이 초과한 아파트를 취득한 경우 대출 불가\n\n-# 청년 전세대출\n1. 신청일 기준 만 19세 이상, 잔금일 기준 만 34세 이하의 내국인\n2. 근로소득자(현 직장 1개월 이상 재직), 소득금액증명원 발급이 가능한 사업소득자, 기타 소득자 또는 무소득자\n3. 부부합산 무주택 및 합산 연소득 7천만원 이하인 고객\n\n* 적용금리\n(조회기준일: 2024.02.02, 현재, 세전, 연%)\n- 고정금리 전세대출\n| 기준금리                  | 가산금리  | 최저금리  | 최고금리  |\n|-----------------------|-------|-------|-------|\n| 기간별 고정금리: 3.60%~3.71% | 0.50% | 4.10% | 4.21% |\n\n- 청년 전세대출\n| 기준금리                  | 가산금리  | 최저금리  | 최고금리  |\n|-----------------------|-------|-------|-------|\n| 신규취급액기준 COFIX(6개월) 3.84% | -0.33% ~ 0.08% | 3.51% | 3.92% |\n\n- 전세대출\n| 기준금리                  | 가산금리  | 최저금리  | 최고금리  |\n|-----------------------|-------|-------|-------|\n| 신규취급액기준 COFIX(6개월) 3.84% | -0.32% ~ 2.37% | 3.52% | 6.21% |\n"
  },
  "주거래자유적금": {
    "category": "예금 · 적금",
    "pd_info": "\n* 상품요약\n상품종류: 목돈모으기(적립식예금)\n가입대상: 만 17세 이상 실명의 개인 및 개인사업자(1인 최대 3계좌)\n가입기간: 6개월 ~ 36개월\n가입금액: 월 1천원 이상 3백만원 이하\n\n- 우대조건\n최고 연 0.60% (우대조건을 충족하는 경우 만기 해지 시 우대금리를 적용)\n\n- 우대조건1\n급여이체 또는 통신비 자동이체(연 0.3%)\t실적 인정 기간 (주1)동안 3개월 이상 급여이체 또는 통신비 자동이체 실적이 있는 경우\n> 급여이체: 건당 50만원 이상, 급여이체 인정기준 (주2)에 해당하는 경우\n\n- 우대조건2\n통신비자동이체: 케이뱅크 입출금통장 또는 케이뱅크 카드로 통신비(통신 3사 KT,SKT,LGU+)자동이체 실적이 있는 경우\n> 케이뱅크 체크카드(연 0.3%)\t실적 인정 기간 동안 3개월 이상 케이뱅크 체크카드 실적이 있는 경우\n> 케이뱅크 체크카드: 월 20만원 이상 사용(월 산정기준: 매월 1일부터 말일)\n"
  },
  "챌린지박스": {
    "category": "예금 · 적금",
    "pd_info": "\n* 상품요약\n가입대상: 당행 입출금통장을 보유한 실명의 개인 및 개인사업자 (1인 최대 10계좌)\n예금종류: 입출금이 자유로운 예금\n목표금액: 1만원 ~ 500만원\n목표기간(모을기간): 30일 ~ 200일\n목표일: 가입일을 포함하여 목표기간이 도래한 날\n\n* 적용금리\n(조회기준일: 2024.02.02, 현재, 세전, 연%)\n기본금리 + 우대금리\n기본금리: 1.50%\n우대금리: 2.50%\n※ 목표일까지 「자동 모으기 서비스」를 통해 '모으기 성공' 조건을 모두 충족한 계좌에 한하여 우대금리를 적용\n"
  },
  "코드K자유적금": {
    "category": "예금 · 적금",
    "pd_info": "\n* 상품요약\n상품종류: 목돈모으기(적립식예금)\n가입대상: 만 17세 이상 실명의 개인 및 개인사업자(1인 최대 15계좌)\n가입기간: 1개월, 3개월, 6개월, 1년, 2년, 3년\n가입금액: 1천원 이상 30만원 이하\n적립한도: 월 최대 30만원(원단위, 자유적립식)\n\n* 세제혜택\n본인 한도 내 비과세종합저축으로 가입 가능\n\n* 이자지급방법\n만기일시지급식\n\n* 적용 금리\n(조회기준일: 2024.02.02, 현재, 세전, 연%)\n| 가입기간 | 기본금리  | 최고금리 (우대금리포함) |\n|------|-------|---------------|\n| 1개월  | 3.30% | 3.30%         |\n| 3개월  | 3.50% | 3.50%         |\n| 6개월  | 3.60% | 10.00%1)      |\n| 1년   | 4.30% | 4.30%         |\n| 2년   | 4.35% | 4.35%         |\n| 3년   | 4.40% | 4.40%         |\n\n1) 「웰컴선물 연 10% 적금 이벤트」를 통해 가입 시 최고 연 10.00%(기본 연 3.60%+우대 연 6.40%)적용 가능\n"
  },
  "코드K정기예금": {
    "category": "예금 · 적금",
    "pd_info": "\n* 상품요약\n상품종류: 목돈굴리기(거치식예금)\n가입대상: 만 17세 이상 실명의 개인 및 개인사업자\n가입기간: 1개월 ~ 36개월\n가입금액: 100만원 이상 ('22년 6월 15일 이후 신규계좌 적용)\n\n* 세제혜택\n본인 한도 내 비과세종합저축으로 가입 가능\n\n* 이자지급방법\n만기일시지급식\n\n* 이자계산방법\n예치 금액에 대해 예치된 기간만큼 약정 금리를 적용하여 이자 지급\n※ 1백만원을 1년동안 예치 시, 세전 37,101원을 받을 수 있습니다.\n(연 3.7% 적용 시, '24.01.16. 기준)\n\n* 부분인출\n2회 가능, 중도해지금리 적용\n단, 예금잔액이 최소가입금액 이하거나 비과세로 가입한 경우 부분인출 불가능\n\n* 적용 금리\n| 가입기간           | 기본금리  | 최고금리 (우대금리포함) |\n|----------------|-------|---------------|\n| 1개월(30일)이상     | 3.10% | 3.10%         |\n| 3개월(90일)이상     | 3.60% | 3.60%         |\n| 6개월(180일)이상    | 3.70% | 3.70%         |\n| 12개월(365일)이상   | 3.70% | 3.70%         |\n| 24개월(720일)이상   | 3.40% | 3.40%         |\n| 36개월(1,095일)이상 | 3.40% | 3.40%         |\n"
  },
  "플러스박스": {
    "category": "예금 · 적금",
    "pd_info": "\n* 상품요약\n가입대상: 당행 입출금통장을 보유한 실명의 개인 및 개인사업자(1인 최대 10계좌)\n예금종류: 입출금이 자유로운 예금\n가입금액: 보유한 플러스박스 계좌 잔액을 모두 합산하여 최대 10억원까지 입금 가능\n가입기간: 제한없음\n\n* 적용금리\n(조회기준일: 2024.02.02, 현재, 세전, 연%)\n적용금리 : 연 2.30%\n이자계산방법 : 일자별 최종 잔액에 대하여 약정된 금리를 적용한 일별이자를 합산\n이자결산지급일 : 매월 넷째주 토요일\n「바로 이자받기」 : 이자지급일이 도래하기 전이라도 최초 예금일(또는 지난 이자지급일)부터 「바로 이자받기」 신청 전일까지의 이자를 바로 받을 수 있습니다.\n이 예금으로 이자가 입금되며, 이자 입금 후 예금의 잔액이 가입금액 한도를 초과하는 경우 초과금액은 연결계좌로 자동 입금 됩니다.\n"
  },
  "플러스체크카드": {
    "category": "카드",
    "pd_info": "\n* 무제한 기본 캐시백\n이용 실적 조건은 물론 캐시백 한도 없이 국·내외 모든 가맹점에서 0.3% 캐시백\n실적 조건 및 캐시백 한도 없이 국내외 모든 가맹점에서 0.3% 캐시백이 지급됩니다.\n캐시백률은 결제 건당 적용되며 1원 미만은 절사됩니다.\n\n* 최대 3만원 특별 캐시백\n마트 · 배달 · 주유 · 아울렛 등 추가 3% 특별 캐시백\n| 구분       | 적용 가맹점                    |\n|----------|---------------------------|\n| 장보기      | 쿠팡, 마켓컬리, 이마트, 홈플러스, 롯데마트 |\n| 배달음식     | 배달의 민족, 요기요, 쿠팡이츠         |\n| 여행, 골프   | 여기어때, 야놀자, 스크린골프 업종       |\n| 주유       | GS칼텍스, SK에너지              |\n| 백화점, 아울렛 | 현대, 신세계, 롯데               |\n\n단, 브랜드별 1일 1회 캐시백 제공\n\n결제 건별 최대 캐시백 : 1,000원\n전월실적 30만원 이상 : 10,000원 한도\n전월실적 50만원 이상 : 20,000원 한도\n전월실적 60만원 이상 : 30,000원 한도\n"
  },
  "한국투자증권": {
    "category": "제휴",
    "pd_info": "\n* 이벤트 기간 : 2024년 1월 1일 ~ 3월 31일\n\n* 혜택1) 국내주식 1주\n- 한국투자증권 최초 신규고객 혜택으로 한국투자증권 앱에서 주식 추첨 시 5영업일 이내 지급(100%지급)\n- 신규고객 혜택은 위 경로를 통해 국내주식 추첨을 정상 신청한 고객에 한하여 지급\n- KOSPI200에 편입된 주식 중 랜덤으로 1주 증정\n(평균 5천원 상당, 단, 한국금융지주, 기업은행, 카카오, 카카오뱅크 제외)\n\n* 혜택2-1) 해외주식 투자지원금 $30\n한국투자증권 해외주식거래 서비스 최초 신청 고객\n한국투자증권 앱에서 이벤트 신청 시 즉시 주식계좌로 입금\n지급된 $30은 31일간 출금 및 환전 불가(캘린더데이 기준)\n\n* 혜택2-2) 해외주식 온라인 거래수수료 및 환전 우대 혜택\n한국투자증권 해외주식거래 최초 신청고객(영업점 계좌 제외, 해외주식거래 신청 필수)\n\n수수료 혜택\n- 최초 1개월 : 해외주식 매수 시 국내수수료 + 해외수수료 0%(단, SEC Fee(기타거래세) 별도 : 미국 0.0008%(매도 시), 중국 0.002%(매수/매도 시))\n- 최초 1개월 후 : 11개월 간 (미국 기준)국내수수료 0.04% + 해외수수료 0.05% 징구(제비용 별도)\n- 우대 수수료 적용 국가 : 미국, 홍콩, 중국, 일본(국가별 해외수수료 상이. 제비용 별도)\n\n환전우대 혜택\n- 적용 기간 : 해외주식거래 신청일로부터 12개월, 이벤트 신청계좌에서 혜택 적용 기간 내 1원 이상 체결 시 동일 혜택 자동 연장\n- USD : 90% / CNY, HKD, JPY, EUR : 80%\n\n* 혜택3) 거래이벤트 최대 $600\n한국투자증권 뱅키스 주식계좌로 해외주식 거래한 고객(이벤트 신청 필수)\n해당 이벤트 혜택 지급은 이벤트 신청 기준 선착순 월별 5,000명이며 조기마감 될 수 있습니다.\n이벤트 신청월 말일까지 누적 체결금액에 따라 혜택 제공\n- 1천만원 이상 ~ 5천만원 미만 : $20\n- 5천만원 이상 ~ 1억원 미만 : $50\n- 1억원 이상 ~ 3억원 미만 : $100\n- 3억원 이상 ~ 5억원 미만 : $200\n- 5억원 이상 ~ 10억원 미만 $400 (100명 추첨, 미 당첨자에게는 $200지급)\n- 10억원 이상 : $600 (100명 추첨, 미 당첨자에게는 $200지급)\n10억원 이상 거래 시 $600, $400 각 혜택으로 2회 추첨 기회 제공\n"
  },
  "돈나무키우기": {
    "category": "서비스",
    "pd_info": "\n돈이 자라는 돈나무를 키우며 매일 현금 보상 받아요.\n돈나무에 물을 주거나 미션을 수행하고 받은 영양제를 주면 돈나무가 자라고 현금을 받을 수 있어요.\n\n* 돈나무에서 현금보상 받는 방법\n - 하루에 한번 물을 주면 보상을 받아요. 물 주기는 한국 시간 자정을 기준으로 수행 가능한 횟수가 초기화돼요.\n - 돈나무 레벨이 팔랑초가 되면 다음부터 레벨업 할 때마다 보상을 받아요.\n - 돈나무가 다 자라면 랜덤으로 최대 10만원까지 보상받을 수 있어요.\n - 돈나무가 다 자라면 새로운 돈나무를 다시 키울 수 있고, 다 키운 돈나무는 사라져요.\n\n* 돈나무 영양제를 받는 방법\n서비스 우측 상단에 있는 미션하기 버튼을 누르면 오늘 수행할 수 있는 미션을 확인할 수 있어요.\n - '구경하기', '알아보기', '보러가기' 미션은 해당 페이지에 방문만 해도 영양제가 지급돼요.\n - '내 대출 한도 조회' 미션은 대출 한도/금리 조건을 확인하면 자동으로 영양제가 지급돼요.\n - 미션은 한국 시간 자정을 기준으로 수행 가능한 종류와 횟수가 초기화돼요.\n서비스 최초 시작 다음 날부터 3일 연속 돈나무 키우기 서비스를 방문하면 영양제가 지급돼요.\n※ 해당 서비스는 회사의 사정에 따라 사전 안내 없이 변경/종료될 수 있어요.\n\n* 돈나무 키우기 알림 안내\n\n물 주기, 미션을 놓치지 않도록 알려드려요.\n - 물 주기 알림 : 일 1회\n - 미션 알림 : 주 1회\n미션과 친구초대를 성공할 때마다 안내해 드려요."
  },
  "내신용관리": {
    "category": "서비스",
    "pd_info": "\n내신용관리 서비스는 맞춤형 정보로 고객들의 신용점수를 관리하여 이후 대출 서비스들을 쉽게 사용가능하게하는 서비스로 아래 기능들을 제공합니다.\n\n* 신용점수 올리기\nKT통신사를 이용하시는 고객님은 터치 한 번으로 신용점수를 올릴 수 있습니다.\n\n* 신용점수 비교\n또래 그룹들간의 신용점수와 카드값, 대출잔금 등을 비교하여 신용관리를 도와드립니다.\n\n* 맞춤형 상품 추천\n신용점수 기반 한도를 조회해 맞춤형 금융상품을 안내해드립니다.\n\n* 신용정보 업데이트 알림\n신용정보 변동내역이 생기면 앱 내 피드로 알려드립니다."
  },
  "머니톡": {
    "category": "서비스",
    "pd_info": "\n제테크, 생활 혜택, 부동산, 대출/보험, 사회이슈 트렌드 등 다양한 생활경제 정보 및 금융 관련 시사 이슈들을 테마별로 구독할 수 있는 서비스입니다.\n이러한 정보를 통해 사용자는 부자가 되는 습관을 만들어볼 수 있습니다."
  },
  "오늘의생활시세": {
    "category": "서비스",
    "pd_info": "\n오늘의 생활시세 서비스는 매일 변동되는 주유비와 식재료비 그리고 환율 등을 한눈에 확인할 수 있는 서비스입니다.\n오늘의 유가 정보를 안내하고 각 지역 내 저렴한 주유소 확인이 가능합니다. 이를 통해 최근 중동 정세가 불안해지며 오르고 있는 기름값 부담을 조금이나마 줄일 수 있습니다.\n또한, 생활하면서 자주 찾는 쌀, 계란, 우유 등 식재료와 관련한 시세도 확인할 수 있어 최근 시세와 비교해 합리적인 소비를 결정할 수 있게 도와줍니다.\n마지막으로, 매일 전세계 21개국 환율의 최근 등락을 비교해주며 최저가 환율 알림 받기를 설정해두면 최근 한 달 내 최저가를 기록한 환율을 알림으로 받을 수 있습니다. 이를 잘 활용하면 해외여행을 준비할 때 보다 저렴한 가격으로 환전을 진행할 수 있습니다."
  },
  "오늘의쿠폰": {
    "category": "서비스",
    "pd_info": "\n캐시백 할인 쿠폰 서비스로 일상 속 자주 쓰는 분야의 캐시백 쿠폰을 제공하는 서비스입니다.\n매주 발급되는 다양한 쿠폰 중에서 고객이 원하는 쿠폰을 골라서 받아 사용할 수 있습니다. \n배달앱·편의점·주유소·카페 등 고객들이 자주 이용하는 19개 브랜드에서 브랜드별로 최대 3000원까지 캐시백 혜택을 제공하며 모든 쿠폰은 해당 브랜드에서 케이뱅크 체크카드로 결제 시 사용이 가능합니다.\n\n오늘의 쿠폰의 경우 다른 할인 쿠폰과는 다르게 매장에서 쿠폰을 제시하거나 앱에 등록할 필요 없이 케이뱅크 체크카드로 결제만 하면 쿠폰 금액만큼 케이뱅크 체크카드 연결 계좌로 자동 입금돼 편리하게 이용할 수 있습니다. \n캐시백 입금 시점은 결제 후 바로 지급됩니다."
  },
  "우리가게매출관리": {
    "category": "서비스",
    "pd_info": "\n우리가게매출관리 서비스는 개인 사업자들이 편리하게 매출과 입금을 관리할 수 있도록 돕는 서비스입니다.\n우리가게매출관리 서비스는 아래 2가지 기능을 제공합니다.\n\n* 입금추적 캘린더\n\n당일 매출액 기준으로 카드사로부터 정상 입금된 내역과 미입금 내역을 확인할 수 있습니다.\n미입금 내역의 경우 입금 지연 사유를 실시간으로 분석하여 안내해 줍니다.\n\n* 매출입금 캘린더\n\n매출 내역과 입금 내역을 일별, 월별로 확인할 수 있습니다.\n배달 앱 3사(배달의민족, 요기요, 쿠팡이츠)의 카드매출 정보도 조회할 수 있습니다.\n이를 통해 개인 사업자들이 매출과 입금 내역을 편리하게 관리할 수 있도록 지원하는 서비스라고 할 수 있습니다."
  },
  "행운상자": {
    "category": "서비스",
    "pd_info": "\n행운상자란? 상자를 열 때마다 현금 100%당첨이 됩니다. 매일 1명 10만원 당첨이되며 당첨금은 현금으로 바로 입금 됩니다.\n\n1. 행운상자 100% 받기\n(1) 친구에게 공유하기\n공유할 수 있는 친구 수에는 제한이 없어요. 단, 동일한 친구에게는 한 번만 공유할 수 있어요.\n\n(2) 친구가 생애 처음으로 케이뱅크에 가입한 경우\n나와 친구 각각 행운상자를 100개씩 받을 수 있어요.\n\n(3) 친구가 이미 케이뱅크 회원인 경우\n나와 친구 각각 행운상자를 1개씩 받을 수 있어요.\n\n2. 10만원 당첨확률 올리기\n(1) 행운상자 열어서 당첨금 확인하기\n받은 행운상자를 열어 당첨금액을 확인하세요. 상자 별로 최소 20원에서 최대 10만원까지 당첨될 수 있어요.\n\n(2) 확률을 더블로 올리기\n당첨금액이 마음에 들지 않으면 [줍줍대신 10만원에 베팅]을 눌러, 다음 번 당첨확률을 더블로 만들어보세요.\n\n(3) 최대 1024배의 당첨확률\n최대 10회 연속하여 행운상자를 [줍줍대신 10만원에 베팅]할 수 있으며, 이 때 10만원 당첨확률은 1024배 높아져요."
  }
}